Dehaze.py
Dehaze-0.0.4.dist-info/LICENSE
Dehaze-0.0.4.dist-info/METADATA
Dehaze-0.0.4.dist-info/WHEEL
Dehaze-0.0.4.dist-info/top_level.txt
Dehaze-0.0.4.dist-info/RECORD
