Metadata-Version: 2.1
Name: Dehaze
Version: 0.0.4
Summary: A Haze remover using Dark Channel Prior
Home-page: https://github.com/parmishh
Author: Paramjit Singh
License: UNKNOWN
Keywords: Dehazer,single image dehazer,image-dehazer,Dark Channel Prior,Foggremover,defogging
Platform: UNKNOWN
Classifier: Programming Language :: Python :: 3
Classifier: License :: OSI Approved :: MIT License
Classifier: Operating System :: OS Independent
Requires-Python: >=3.6
License-File: LICENSE
Requires-Dist: image-dehazer
Requires-Dist: Pillow
Requires-Dist: numpy
Requires-Dist: opencv-python
Requires-Dist: moviepy
Requires-Dist: rembg
